Workbook

Sheet Expense
A1: Date | B1: Items | C1: Expenses | D1: Category | E1: Cost Type
A2: 44470 | B2: Medicine | C2: 2300 | D2: Essentials | E2: =IF(C2>2000,"Over Budget","Within Budget") -> Over Budget
A3: 44470 | B3: Online shopping | C3: 767 | D3: Non Essentials | E3: =IF(C3>2000,"Over Budget","Within Budget") -> Within Budget
A4: 44470 | B4: Other essential items | C4: 2500 | D4: Essentials | E4: =IF(C4>2000,"Over Budget","Within Budget") -> Over Budget
A5: 44473 | B5: Vegetables & Fruit | C5: 710 | D5: Essentials | E5: =IF(C5>2000,"Over Budget","Within Budget") -> Within Budget
A6: 44473 | B6: Fish & Chicken | C6: 760 | D6: Non Essentials | E6: =IF(C6>2000,"Over Budget","Within Budget") -> Within Budget
A7: 44476 | B7: Gifts | C7: 1900 | D7: Non Essentials | E7: =IF(C7>2000,"Over Budget","Within Budget") -> Within Budget
A8: 44477 | B8: Ordering food | C8: 450 | D8: Non Essentials | E8: =IF(C8>2000,"Over Budget","Within Budget") -> Within Budget
A9: 44484 | B9: Movie with friends | C9: 620 | D9: Non Essentials | E9: =IF(C9>2000,"Over Budget","Within Budget") -> Within Budget
A10: 44485 | B10: Mobile Bill Payment | C10: 470 | D10: Essentials | E10: =IF(C10>2000,"Over Budget","Within Budget") -> Within Budget
A11: 44487 | B11: Online shopping | C11: 970 | D11: Non Essentials | E11: =IF(C11>2000,"Over Budget","Within Budget") -> Within Budget
A12: 44487 | B12: Medicine | C12: 1075 | D12: Essentials | E12: =IF(C12>2000,"Over Budget","Within Budget") -> Within Budget
A13: 44488 | B13: Ordering food | C13: 489 | D13: Non Essentials | E13: =IF(C13>2000,"Over Budget","Within Budget") -> Within Budget
... A51: 44553 | B51: Vegetables & Fruit | C51: 450 | D51: Essentials | E51: =IF(C51>2000,"Over Budget","Within Budget") -> Within Budget
C52: =SUM(C2:C51) -> 57045.27

Sheet Tasks
B1: Task to Perform
B2: How many times has Priya done transactions on online shopping, ordering food and gifts?
B3: Calculate the total expenses against each distinct item.
B4: Arrange the item-wise total expense in descending order.
B5: Present the item-wise total expense through a chart that shows the expense of each item as a percentage of the total expense. Don’t take trip expenses into consideration. | C5: create table to show item wise total expense
B6: Present the expense pattern visually over 3 months.
B7: Add a new column to the data table, name it as “Category” and apply data validation with drop-down fields as “Essentials” and “Non-essentials”. Fill in the column.
B8: Add another new column and name it as “Cost Type”. For each item, if the expense is more than 2000, tag it as “Over budget”, else, tag it as “Within budget”.
B9: Mention the ways how Priya can reduce her expenses. Justify each point.

Sheet Sheet1
A1: Q1-How many times has Priya done transactions on online shopping, ordering food and gifts?
A3: online shopping : | E3: =COUNTIF(Expense!B:B,"Online shopping") -> 6
A4: ordering food : | E4: =COUNTIF(Expense!B:B,"Ordering food") -> 5
A5: Gifts: | E5: =COUNTIF(Expense!B:B,"Gifts") -> 4
A6: total | E6: =SUM(E3:E5) -> 15
A9: Q2-Calculate the total expenses against each distinct item.
A11: Items | B11: Total Expense
A12: Medicine | B12: =SUMIF(Expense!B:B,Sheet1!A12,Expense!C:C) -> 7775
A13: Online shopping | B13: =SUMIF(Expense!B:B,Sheet1!A13,Expense!C:C) -> 7464
A14: Other essential items | B14: =SUMIF(Expense!B:B,Sheet1!A14,Expense!C:C) -> 10194.1
A15: Vegetables & Fruit | B15: =SUMIF(Expense!B:B,Sheet1!A15,Expense!C:C) -> 3217
A16: Fish & Chicken | B16: =SUMIF(Expense!B:B,Sheet1!A16,Expense!C:C) -> 3342
A17: Gifts | B17: =SUMIF(Expense!B:B,Sheet1!A17,Expense!C:C) -> 5688
A18: Ordering food | B18: =SUMIF(Expense!B:B,Sheet1!A18,Expense!C:C) -> 1857
A19: Movie with friends | B19: =SUMIF(Expense!B:B,Sheet1!A19,Expense!C:C) -> 2586
A20: Mobile Bill Payment | B20: =SUMIF(Expense!B:B,Sheet1!A20,Expense!C:C) -> 1411.26
A21: Cab to office | B21: =SUMIF(Expense!B:B,Sheet1!A21,Expense!C:C) -> 1510.91
A22: Trip | B22: =SUMIF(Expense!B:B,Sheet1!A22,Expense!C:C) -> 12000
A26: Q3-Arrange the item-wise total expense in descending order.
A28: Items | B28: Total Expense
A29: Trip | B29: =SUMIF(Expense!B:B,Sheet1!A29,Expense!C:C) -> 12000
A30: Other essential items | B30: =SUMIF(Expense!B:B,Sheet1!A30,Expense!C:C) -> 10194.1
A31: Medicine | B31: =SUMIF(Expense!B:B,Sheet1!A31,Expense!C:C) -> 7775
A32: Online shopping | B32: =SUMIF(Expense!B:B,Sheet1!A32,Expense!C:C) -> 7464
A33: Gifts | B33: =SUMIF(Expense!B:B,Sheet1!A33,Expense!C:C) -> 5688
A34: Fish & Chicken | B34: =SUMIF(Expense!B:B,Sheet1!A34,Expense!C:C) -> 3342
A35: Vegetables & Fruit | B35: =SUMIF(Expense!B:B,Sheet1!A35,Expense!C:C) -> 3217
A36: Movie with friends | B36: =SUMIF(Expense!B:B,Sheet1!A36,Expense!C:C) -> 2586
A37: Ordering food | B37: =SUMIF(Expense!B:B,Sheet1!A37,Expense!C:C) -> 1857
A38: Cab to office | B38: =SUMIF(Expense!B:B,Sheet1!A38,Expense!C:C) -> 1510.91
A39: Mobile Bill Payment | B39: =SUMIF(Expense!B:B,Sheet1!A39,Expense!C:C) -> 1411.26
